altstore_proxy/__init__.py
altstore_proxy/run.py
altstore_proxy/providers/__init__.py
altstore_proxy/providers/notifications.py
altstore_proxy/providers/shared_state.py
altstore_proxy/providers/version.py
altstore_proxy-1.3.8.dist-info/LICENSE.md
altstore_proxy-1.3.8.dist-info/METADATA
altstore_proxy-1.3.8.dist-info/WHEEL
altstore_proxy-1.3.8.dist-info/entry_points.txt
altstore_proxy-1.3.8.dist-info/top_level.txt
altstore_proxy-1.3.8.dist-info/RECORD
