Metadata-Version: 2.1
Name: altstore-proxy
Version: 1.3.8
Summary: A simple proxy for slow AltStore servers
Home-page: https://github.com/rix1337/AltStore-Proxy
Author: rix1337
Author-email: 
License: UNKNOWN
Platform: UNKNOWN
Classifier: Programming Language :: Python :: 3
Classifier: License :: OSI Approved :: MIT License
Classifier: Operating System :: OS Independent
License-File: LICENSE.md
Requires-Dist: bottle (==0.12.25)
Requires-Dist: requests (==2.31.0)
Requires-Dist: tqdm (==4.66.4)
